{
  "exp_name": "csci_ECG_exp3_run0_seed3407",
  "num_splits": 100,
  "per_horizon": {
    "h1": {
      "obs_mae": "3.3523 +- 0.5070",
      "obs_rmse": "5.7379 +- 0.8536",
      "miss_mae": "3.7787 +- 0.6214",
      "miss_rmse": "6.2932 +- 0.9882",
      "oracle_mae": "3.1568 +- 0.4735",
      "oracle_rmse": "5.4822 +- 0.9285"
    },
    "h2": {
      "obs_mae": "3.3421 +- 0.4988",
      "obs_rmse": "5.7163 +- 0.8474",
      "miss_mae": "3.8081 +- 0.6258",
      "miss_rmse": "6.3376 +- 1.0219",
      "oracle_mae": "3.1530 +- 0.4749",
      "oracle_rmse": "5.4767 +- 0.9243"
    },
    "h3": {
      "obs_mae": "3.3927 +- 0.5187",
      "obs_rmse": "5.8134 +- 0.8787",
      "miss_mae": "3.8259 +- 0.6119",
      "miss_rmse": "6.3478 +- 0.9664",
      "oracle_mae": "3.1940 +- 0.4889",
      "oracle_rmse": "5.5672 +- 0.9574"
    },
    "h4": {
      "obs_mae": "3.4100 +- 0.5150",
      "obs_rmse": "5.8016 +- 0.8702",
      "miss_mae": "3.8003 +- 0.6262",
      "miss_rmse": "6.2932 +- 0.9664",
      "oracle_mae": "3.2233 +- 0.4873",
      "oracle_rmse": "5.5749 +- 0.9500"
    },
    "h5": {
      "obs_mae": "3.4149 +- 0.5193",
      "obs_rmse": "5.8282 +- 0.8629",
      "miss_mae": "3.8148 +- 0.6353",
      "miss_rmse": "6.3586 +- 1.0030",
      "oracle_mae": "3.2138 +- 0.4875",
      "oracle_rmse": "5.5756 +- 0.9431"
    },
    "h6": {
      "obs_mae": "3.4502 +- 0.5293",
      "obs_rmse": "5.9034 +- 0.8904",
      "miss_mae": "3.8424 +- 0.6413",
      "miss_rmse": "6.4204 +- 0.9934",
      "oracle_mae": "3.2410 +- 0.4966",
      "oracle_rmse": "5.6346 +- 0.9703"
    },
    "h7": {
      "obs_mae": "3.4414 +- 0.5188",
      "obs_rmse": "5.8532 +- 0.8760",
      "miss_mae": "3.8129 +- 0.6248",
      "miss_rmse": "6.3492 +- 0.9732",
      "oracle_mae": "3.2617 +- 0.4929",
      "oracle_rmse": "5.6210 +- 0.9560"
    },
    "h8": {
      "obs_mae": "3.4670 +- 0.5225",
      "obs_rmse": "5.9085 +- 0.8852",
      "miss_mae": "3.8458 +- 0.6393",
      "miss_rmse": "6.3932 +- 0.9729",
      "oracle_mae": "3.2789 +- 0.4957",
      "oracle_rmse": "5.6508 +- 0.9674"
    },
    "h9": {
      "obs_mae": "3.5030 +- 0.5357",
      "obs_rmse": "5.9768 +- 0.9133",
      "miss_mae": "3.8339 +- 0.6433",
      "miss_rmse": "6.4049 +- 0.9837",
      "oracle_mae": "3.3176 +- 0.5124",
      "oracle_rmse": "5.7260 +- 0.9991"
    },
    "h10": {
      "obs_mae": "3.4692 +- 0.5235",
      "obs_rmse": "5.9133 +- 0.8919",
      "miss_mae": "3.8342 +- 0.6248",
      "miss_rmse": "6.4240 +- 0.9562",
      "oracle_mae": "3.2762 +- 0.5008",
      "oracle_rmse": "5.6657 +- 0.9732"
    },
    "h11": {
      "obs_mae": "3.4805 +- 0.5251",
      "obs_rmse": "5.9656 +- 0.9024",
      "miss_mae": "3.8463 +- 0.6346",
      "miss_rmse": "6.4547 +- 0.9660",
      "oracle_mae": "3.2772 +- 0.5009",
      "oracle_rmse": "5.6999 +- 0.9814"
    },
    "h12": {
      "obs_mae": "3.4728 +- 0.5206",
      "obs_rmse": "5.9400 +- 0.9034",
      "miss_mae": "3.8394 +- 0.6241",
      "miss_rmse": "6.4206 +- 0.9825",
      "oracle_mae": "3.2918 +- 0.5030",
      "oracle_rmse": "5.7003 +- 0.9872"
    }
  },
  "overall": {
    "obs_mae": "3.4330 +- 0.5195",
    "obs_rmse": "5.8632 +- 0.8813",
    "miss_mae": "3.8236 +- 0.6294",
    "miss_rmse": "6.3748 +- 0.9811",
    "oracle_mae": "3.2404 +- 0.4929",
    "oracle_rmse": "5.6146 +- 0.9615"
  }
}